xgbse/__init__.py
xgbse/_base.py
xgbse/_debiased_bce.py
xgbse/_feature_extractors.py
xgbse/_kaplan_neighbors.py
xgbse/_meta.py
xgbse/_stacked_weibull.py
xgbse/converters.py
xgbse/extrapolation.py
xgbse/metrics.py
xgbse/non_parametric.py
xgbse-0.3.3.dist-info/LICENSE
xgbse-0.3.3.dist-info/METADATA
xgbse-0.3.3.dist-info/WHEEL
xgbse-0.3.3.dist-info/RECORD
