Metadata-Version: 2.1
Name: xgbse
Version: 0.3.3
Summary: Improving XGBoost survival analysis with embeddings and debiased estimators
Home-page: https://github.com/loft-br/xgboost-survival-embeddings
Author: Loft Data Science Team
Author-email: bandits@loft.com.br
Requires-Python: >=3.9
Classifier: Programming Language :: Python :: 3
Classifier: Programming Language :: Python :: 3.9
Classifier: Programming Language :: Python :: 3.10
Classifier: Programming Language :: Python :: 3.11
Classifier: Programming Language :: Python :: 3.12
Requires-Dist: joblib (>=1.4.2,<2.0.0)
Requires-Dist: lifelines (>=0.29.0,<0.30.0)
Requires-Dist: numpy (>=1.26.4,<2.0.0)
Requires-Dist: pandas (>=2.2.0,<3.0.0)
Requires-Dist: scikit-learn (>=1.5.0,<2.0.0)
Requires-Dist: xgboost (>=2.1.0,<3.0.0)
Project-URL: Repository, https://github.com/loft-br/xgboost-survival-embeddings
